mlhelp
