Metadata-Version: 1.0
Name: mlhelp
Version: 1.9
Summary: Exists cause of Package problems
Home-page: UNKNOWN
Author: Sai Krishna
Author-email: saimanthena13579@gmail.com
License: UNKNOWN
Platform: UNKNOWN
